{
  "ok": true,
  "rows": [
    { "fecha": "20/08/2025", "hora": "18:17", "fc": 121, "spo2": 98, "patadas": 2 },
    { "fecha": "20/08/2025", "hora": "09:24", "fc": 75, "spo2": 93, "patadas": 8 },
    { "fecha": "19/08/2025", "hora": "21:23", "fc": 77, "spo2": 93, "patadas": 4 },
    { "fecha": "19/08/2025", "hora": "11:20", "fc": 74, "spo2": 97, "patadas": 5 },
    { "fecha": "18/08/2025", "hora": "19:53", "fc": 71, "spo2": 96, "patadas": 5 },
    { "fecha": "18/08/2025", "hora": "09:36", "fc": 87, "spo2": 93, "patadas": 1 },
    { "fecha": "17/08/2025", "hora": "20:41", "fc": 86, "spo2": 95, "patadas": 6 },
    { "fecha": "17/08/2025", "hora": "08:24", "fc": 92, "spo2": 93, "patadas": 7 },
    { "fecha": "16/08/2025", "hora": "21:49", "fc": 85, "spo2": 98, "patadas": 8 },
    { "fecha": "16/08/2025", "hora": "10:44", "fc": 75, "spo2": 94, "patadas": 8 },
    { "fecha": "15/08/2025", "hora": "20:53", "fc": 86, "spo2": 94, "patadas": 6 },
    { "fecha": "15/08/2025", "hora": "09:40", "fc": 79, "spo2": 96, "patadas": 9 },
    { "fecha": "14/08/2025", "hora": "19:41", "fc": 81, "spo2": 96, "patadas": 8 },
    { "fecha": "14/08/2025", "hora": "08:11", "fc": 86, "spo2": 97, "patadas": 9 },
    { "fecha": "13/08/2025", "hora": "21:53", "fc": 74, "spo2": 97, "patadas": 8 },
    { "fecha": "13/08/2025", "hora": "10:30", "fc": 76, "spo2": 94, "patadas": 5 },
    { "fecha": "12/08/2025", "hora": "22:34", "fc": 86, "spo2": 93, "patadas": 3 },
    { "fecha": "12/08/2025", "hora": "09:18", "fc": 91, "spo2": 98, "patadas": 4 },
    { "fecha": "11/08/2025", "hora": "18:34", "fc": 90, "spo2": 96, "patadas": 8 },
    { "fecha": "11/08/2025", "hora": "09:55", "fc": 89, "spo2": 97, "patadas": 4 },
    { "fecha": "10/08/2025", "hora": "19:23", "fc": 75, "spo2": 95, "patadas": 3 },
    { "fecha": "10/08/2025", "hora": "10:20", "fc": 84, "spo2": 93, "patadas": 4 },
    { "fecha": "09/08/2025", "hora": "19:49", "fc": 76, "spo2": 97, "patadas": 4 },
    { "fecha": "09/08/2025", "hora": "09:33", "fc": 84, "spo2": 96, "patadas": 1 },
    { "fecha": "08/08/2025", "hora": "18:57", "fc": 68, "spo2": 97, "patadas": 6 },
    { "fecha": "08/08/2025", "hora": "12:33", "fc": 81, "spo2": 95, "patadas": 4 },
    { "fecha": "07/08/2025", "hora": "19:45", "fc": 81, "spo2": 95, "patadas": 7 },
    { "fecha": "07/08/2025", "hora": "10:20", "fc": 86, "spo2": 98, "patadas": 2 },
    { "fecha": "06/08/2025", "hora": "21:49", "fc": 95, "spo2": 98, "patadas": 9 },
    { "fecha": "06/08/2025", "hora": "11:36", "fc": 73, "spo2": 95, "patadas": 7 },
    { "fecha": "05/08/2025", "hora": "19:30", "fc": 81, "spo2": 98, "patadas": 1 },
    { "fecha": "05/08/2025", "hora": "09:36", "fc": 83, "spo2": 94, "patadas": 7 },
    { "fecha": "04/08/2025", "hora": "21:30", "fc": 78, "spo2": 97, "patadas": 3 },
    { "fecha": "04/08/2025", "hora": "12:36", "fc": 84, "spo2": 95, "patadas": 5 },
    { "fecha": "03/08/2025", "hora": "21:30", "fc": 93, "spo2": 98, "patadas": 3 },
    { "fecha": "03/08/2025", "hora": "10:27", "fc": 91, "spo2": 98, "patadas": 9 },
    { "fecha": "02/08/2025", "hora": "22:57", "fc": 87, "spo2": 98, "patadas": 4 },
    { "fecha": "02/08/2025", "hora": "10:48", "fc": 72, "spo2": 94, "patadas": 9 },
    { "fecha": "01/08/2025", "hora": "21:57", "fc": 69, "spo2": 96, "patadas": 6 },
    { "fecha": "01/08/2025", "hora": "08:40", "fc": 75, "spo2": 98, "patadas": 7 },
    { "fecha": "31/07/2025", "hora": "19:11", "fc": 74, "spo2": 96, "patadas": 5 },
    { "fecha": "31/07/2025", "hora": "08:30", "fc": 92, "spo2": 94, "patadas": 1 },
    { "fecha": "30/07/2025", "hora": "22:53", "fc": 74, "spo2": 96, "patadas": 7 },
    { "fecha": "30/07/2025", "hora": "10:36", "fc": 72, "spo2": 93, "patadas": 9 },
    { "fecha": "29/07/2025", "hora": "22:49", "fc": 84, "spo2": 95, "patadas": 8 },
    { "fecha": "29/07/2025", "hora": "09:48", "fc": 86, "spo2": 98, "patadas": 2 },
    { "fecha": "28/07/2025", "hora": "21:30", "fc": 83, "spo2": 96, "patadas": 8 },
    { "fecha": "28/07/2025", "hora": "10:11", "fc": 72, "spo2": 96, "patadas": 5 },
    { "fecha": "27/07/2025", "hora": "21:49", "fc": 72, "spo2": 96, "patadas": 5 },
    { "fecha": "27/07/2025", "hora": "08:18", "fc": 71, "spo2": 97, "patadas": 2 },
    { "fecha": "26/07/2025", "hora": "21:53", "fc": 71, "spo2": 97, "patadas": 4 },
    { "fecha": "26/07/2025", "hora": "09:20", "fc": 87, "spo2": 96, "patadas": 2 },
    { "fecha": "25/07/2025", "hora": "21:38", "fc": 90, "spo2": 93, "patadas": 4 },
    { "fecha": "25/07/2025", "hora": "08:24", "fc": 90, "spo2": 96, "patadas": 6 },
    { "fecha": "24/07/2025", "hora": "19:38", "fc": 68, "spo2": 94, "patadas": 8 },
    { "fecha": "24/07/2025", "hora": "08:15", "fc": 69, "spo2": 95, "patadas": 9 },
    { "fecha": "23/07/2025", "hora": "21:41", "fc": 71, "spo2": 96, "patadas": 9 },
    { "fecha": "23/07/2025", "hora": "10:48", "fc": 73, "spo2": 96, "patadas": 4 },
    { "fecha": "22/07/2025", "hora": "18:30", "fc": 85, "spo2": 97, "patadas": 8 },
    { "fecha": "22/07/2025", "hora": "08:20", "fc": 87, "spo2": 97, "patadas": 9 },
    { "fecha": "21/07/2025", "hora": "21:38", "fc": 86, "spo2": 95, "patadas": 2 },
    { "fecha": "21/07/2025", "hora": "11:24", "fc": 89, "spo2": 97, "patadas": 3 },
    { "fecha": "20/07/2025", "hora": "20:53", "fc": 84, "spo2": 96, "patadas": 9 },
    { "fecha": "20/07/2025", "hora": "10:27", "fc": 92, "spo2": 96, "patadas": 8 },
    { "fecha": "19/07/2025", "hora": "21:20", "fc": 95, "spo2": 96, "patadas": 5 },
    { "fecha": "19/07/2025", "hora": "09:52", "fc": 84, "spo2": 96, "patadas": 8 },
    { "fecha": "18/07/2025", "hora": "22:34", "fc": 82, "spo2": 98, "patadas": 8 },
    { "fecha": "18/07/2025", "hora": "08:48", "fc": 86, "spo2": 98, "patadas": 7 },
    { "fecha": "17/07/2025", "hora": "21:30", "fc": 95, "spo2": 98, "patadas": 8 },
    { "fecha": "17/07/2025", "hora": "10:18", "fc": 75, "spo2": 97, "patadas": 5 },
    { "fecha": "16/07/2025", "hora": "22:23", "fc": 90, "spo2": 97, "patadas": 7 },
    { "fecha": "16/07/2025", "hora": "10:40", "fc": 84, "spo2": 95, "patadas": 1 },
    { "fecha": "15/07/2025", "hora": "18:30", "fc": 84, "spo2": 97, "patadas": 8 },
    { "fecha": "15/07/2025", "hora": "08:52", "fc": 82, "spo2": 98, "patadas": 8 },
    { "fecha": "14/07/2025", "hora": "22:57", "fc": 85, "spo2": 96, "patadas": 9 },
    { "fecha": "14/07/2025", "hora": "10:55", "fc": 83, "spo2": 96, "patadas": 5 },
    { "fecha": "13/07/2025", "hora": "22:26", "fc": 73, "spo2": 97, "patadas": 2 },
    { "fecha": "13/07/2025", "hora": "12:24", "fc": 83, "spo2": 93, "patadas": 5 },
    { "fecha": "12/07/2025", "hora": "22:20", "fc": 95, "spo2": 98, "patadas": 3 },
    { "fecha": "12/07/2025", "hora": "09:52", "fc": 91, "spo2": 96, "patadas": 3 },
    { "fecha": "11/07/2025", "hora": "20:11", "fc": 86, "spo2": 97, "patadas": 7 },
    { "fecha": "11/07/2025", "hora": "12:12", "fc": 74, "spo2": 96, "patadas": 9 },
    { "fecha": "10/07/2025", "hora": "21:26", "fc": 68, "spo2": 94, "patadas": 5 },
    { "fecha": "10/07/2025", "hora": "09:44", "fc": 92, "spo2": 96, "patadas": 7 },
    { "fecha": "09/07/2025", "hora": "19:49", "fc": 92, "spo2": 96, "patadas": 7 },
    { "fecha": "09/07/2025", "hora": "09:36", "fc": 86, "spo2": 96, "patadas": 9 },
    { "fecha": "08/07/2025", "hora": "18:49", "fc": 79, "spo2": 97, "patadas": 2 },
    { "fecha": "08/07/2025", "hora": "10:36", "fc": 72, "spo2": 94, "patadas": 5 },
    { "fecha": "07/07/2025", "hora": "21:38", "fc": 74, "spo2": 98, "patadas": 3 },
    { "fecha": "07/07/2025", "hora": "08:24", "fc": 75, "spo2": 95, "patadas": 4 },
    { "fecha": "06/07/2025", "hora": "18:34", "fc": 84, "spo2": 98, "patadas": 9 },
    { "fecha": "06/07/2025", "hora": "09:20", "fc": 80, "spo2": 98, "patadas": 5 },
    { "fecha": "05/07/2025", "hora": "21:45", "fc": 93, "spo2": 95, "patadas": 1 },
    { "fecha": "05/07/2025", "hora": "11:27", "fc": 80, "spo2": 97, "patadas": 1 },
    { "fecha": "04/07/2025", "hora": "18:49", "fc": 76, "spo2": 98, "patadas": 8 },
    { "fecha": "04/07/2025", "hora": "08:20", "fc": 85, "spo2": 93, "patadas": 2 },
    { "fecha": "03/07/2025", "hora": "21:26", "fc": 68, "spo2": 94, "patadas": 7 },
    { "fecha": "03/07/2025", "hora": "12:18", "fc": 75, "spo2": 95, "patadas": 0 },
    { "fecha": "02/07/2025", "hora": "20:23", "fc": 86, "spo2": 93, "patadas": 1 },
    { "fecha": "02/07/2025", "hora": "08:00", "fc": 75, "spo2": 93, "patadas": 2 }
  ]
}
 
 